mmfewshot/__init__.py
mmfewshot/version.py
mmfewshot/classification/__init__.py
mmfewshot/classification/apis/__init__.py
mmfewshot/classification/apis/inference.py
mmfewshot/classification/apis/test.py
mmfewshot/classification/apis/train.py
mmfewshot/classification/core/__init__.py
mmfewshot/classification/core/evaluation/__init__.py
mmfewshot/classification/core/evaluation/eval_hooks.py
mmfewshot/classification/datasets/__init__.py
mmfewshot/classification/datasets/base.py
mmfewshot/classification/datasets/builder.py
mmfewshot/classification/datasets/cub.py
mmfewshot/classification/datasets/dataset_wrappers.py
mmfewshot/classification/datasets/mini_imagenet.py
mmfewshot/classification/datasets/tiered_imagenet.py
mmfewshot/classification/datasets/utils.py
mmfewshot/classification/datasets/pipelines/__init__.py
mmfewshot/classification/datasets/pipelines/loading.py
mmfewshot/classification/models/__init__.py
mmfewshot/classification/models/backbones/__init__.py
mmfewshot/classification/models/backbones/conv4.py
mmfewshot/classification/models/backbones/resnet12.py
mmfewshot/classification/models/backbones/utils.py
mmfewshot/classification/models/backbones/wrn.py
mmfewshot/classification/models/classifiers/__init__.py
mmfewshot/classification/models/classifiers/base.py
mmfewshot/classification/models/classifiers/base_finetune.py
mmfewshot/classification/models/classifiers/base_metric.py
mmfewshot/classification/models/classifiers/baseline.py
mmfewshot/classification/models/classifiers/baseline_plus.py
mmfewshot/classification/models/classifiers/maml.py
mmfewshot/classification/models/classifiers/matching_net.py
mmfewshot/classification/models/classifiers/meta_baseline.py
mmfewshot/classification/models/classifiers/neg_margin.py
mmfewshot/classification/models/classifiers/proto_net.py
mmfewshot/classification/models/classifiers/relation_net.py
mmfewshot/classification/models/heads/__init__.py
mmfewshot/classification/models/heads/base_head.py
mmfewshot-0.1.0.dist-info/LICENSE
mmfewshot-0.1.0.dist-info/METADATA
mmfewshot-0.1.0.dist-info/WHEEL
mmfewshot-0.1.0.dist-info/top_level.txt
mmfewshot-0.1.0.dist-info/RECORD
